RecallAIsh/__init__.py
RecallAIsh/enums.py
RecallAIsh/prompt_manager.py
RecallAIsh/rag_system.py
RecallAIsh/utils.py
RecallAIsh/document_loaders/__init__.py
RecallAIsh/document_loaders/base_loader.py
RecallAIsh/document_loaders/pdf_loader.py
RecallAIsh/document_loaders/web_loader.py
RecallAIsh/vector_store/__init__.py
RecallAIsh/vector_store/base.py
RecallAIsh/vector_store/mongodb_store.py
RecallAIsh/vector_store/pinecone_store.py
RecallAIsh/vector_store/qdrant_store.py
RecallAIsh/web_scraper/__init__.py
RecallAIsh/web_scraper/base.py
RecallAIsh/web_scraper/playwright_scraper.py
RecallAIsh/web_scraper/selenium_scraper.py
recallaish-0.2.5.dist-info/LICENSE
recallaish-0.2.5.dist-info/METADATA
recallaish-0.2.5.dist-info/WHEEL
recallaish-0.2.5.dist-info/top_level.txt
recallaish-0.2.5.dist-info/RECORD
