Metadata-Version: 2.2
Name: RecallAIsh
Version: 0.2.5
Summary: RecallAI is a cutting-edge Retrieval-Augmented Generation (RAG) framework designed for Large Language Models (LLMs). It enhances LLM responses by integrating real-time knowledge retrieval from structured and unstructured data sources.
Home-page: https://github.com/AshishChandpa/RecallAI
Author: Ashish Chandpa
Author-email: chandpa.ashish007@gmail.com
Classifier: Programming Language :: Python :: 3
Classifier: License :: OSI Approved :: MIT License
Classifier: Operating System :: OS Independent
Requires-Python: >=3.10
License-File: LICENSE
Requires-Dist: openai
Requires-Dist: beautifulsoup4
Requires-Dist: requests
Requires-Dist: PyPDF2
Requires-Dist: pymongo
Requires-Dist: pinecone-client
Requires-Dist: qdrant-client
Requires-Dist: playwright
Provides-Extra: pinecone
Requires-Dist: pinecone-client; extra == "pinecone"
Provides-Extra: qdrant
Requires-Dist: qdrant-client; extra == "qdrant"
Provides-Extra: mongodb
Requires-Dist: pymongo; extra == "mongodb"
Provides-Extra: playwright
Requires-Dist: playwright; extra == "playwright"
Dynamic: author
Dynamic: author-email
Dynamic: classifier
Dynamic: description
Dynamic: description-content-type
Dynamic: home-page
Dynamic: provides-extra
Dynamic: requires-dist
Dynamic: requires-python
Dynamic: summary
